BuddyNS/__init__.py
BuddyNS/errors.py
BuddyNS-2.0.3.dist-info/METADATA
BuddyNS-2.0.3.dist-info/WHEEL
BuddyNS-2.0.3.dist-info/top_level.txt
BuddyNS-2.0.3.dist-info/RECORD
