Metadata-Version: 2.1
Name: BuddyNS
Version: 2.0.3
Summary: A python client library to easily consume BuddyNS.com's API
Home-page: https://www.buddyns.com/support/api/
Author: BuddyNS.com
Author-email: support@buddyns.com
License: UNKNOWN
Platform: UNKNOWN
Classifier: Topic :: Internet :: Name Service (DNS)
Classifier: Topic :: Security
Classifier: Programming Language :: Python :: 3.6
Classifier: Programming Language :: Python :: 2.7
Classifier: License :: OSI Approved :: BSD License
Classifier: Operating System :: OS Independent
Classifier: Development Status :: 5 - Production/Stable
Requires-Python: >=2.7
